{"bookId":"22297575","title":"极致产品","author":"周鸿祎","cover":"https://wfqqreader-1252317822.image.myqcloud.com/cover/575/22297575/s_22297575.jpg","version":2035769151,"format":"epub","type":0,"price":29.40,"originalPrice":0,"soldout":0,"bookStatus":1,"payType":4097,"finished":1,"maxFreeChapter":8,"free":0,"mcardDiscount":0,"ispub":1,"cpid":2000000231,"centPrice":2940,"category":"经济理财榜-管理","hasLecture":1,"intro":"周鸿祎作为知名的产品经理之一，一手打造了众多国民级的产品。他关于打造爆款的理念，比如刚需、高频、“小白”思维等，已成为网络热词而被广泛接受。本书是周鸿祎首次系统总结其20年产品经理的心得，不仅将以往的理念进行总结、归纳，而且在与包括各方面创业者、产品经理的碰撞后，将其观念进一步升华，成为迄今为止首部将其产品理念倾囊相授的作品。","lastChapterIdx":48,"paperBook":{"skuId":"12268778"},"chapterSize":48,"updateTime":1618167149,"onTime":1531213357,"unitPrice":0.05,"marketType":0,"isbn":"9787508682884","publisher":"中信出版社","publishTime":"2018-01-01 00:00:00","totalWords":97438,"publishPrice":49.00,"bookSize":465933,"recommended":0,"lectureRecommended":0,"follow":0,"secret":0,"offline":0,"lectureOffline":0,"finishReading":0,"isAutoPay":0,"availables":0,"paid":0,"isChapterPaid":0,"showLectureButton":1,"wxtts":1,"star":83,"ratingCount":579,"ratingDetail":{"one":7,"two":10,"three":65,"four":173,"five":311,"recent":2},"newRating":712,"newRatingCount":521,"newRatingDetail":{"good":371,"fair":143,"poor":7,"recent":2,"myRating":"","title":"值得一读"},"copyrightInfo":{"id":2000000231,"name":"中信出版集团","userVid":168010251},"authorSeg":[{"words":"周鸿祎","highlight":1}]}