{"bookId":"22664120","title":"为什么精英都是时间控","author":"桦泽紫苑","cover":"https://wfqqreader-1252317822.image.myqcloud.com/cover/120/22664120/s_22664120.jpg","version":779116140,"format":"epub","type":0,"price":19.99,"originalPrice":0,"soldout":0,"bookStatus":1,"payType":4097,"finished":1,"maxFreeChapter":12,"free":0,"mcardDiscount":0,"ispub":1,"cpid":2000000324,"centPrice":1999,"category":"个人成长榜-人生哲学","hasLecture":1,"lPushName":"将大脑机能发挥到极致的时间管理术","intro":"精英都在践行的高效时间管理术！作者曾是差点被精神压力打垮、被工作“忙杀”的神经科医生，在决心改变自己的生活方式后，发现了将大脑机能发挥到极致的时间管理术，实现了一天之中完成4个人才能完成的工作，还拥有一般人2倍以上的自由时间。 书中分享的时间管理术并不仅仅是作者个人的成功经验，而是加入了新近的脑科学和心理学知识，作者用两年时间将自己的时间管理方法体系化，形成了他的“神之时间管理术”。","lastChapterIdx":40,"paperBook":{"skuId":"12298039"},"chapterSize":40,"updateTime":1618302830,"onTime":1542334455,"unitPrice":0.05,"marketType":0,"isbn":"9787540484705","publisher":"湖南文艺出版社","publishTime":"2018-03-01 00:00:00","totalWords":97287,"publishPrice":45.00,"bookSize":536800,"recommended":0,"lectureRecommended":0,"follow":0,"secret":0,"offline":0,"lectureOffline":0,"finishReading":0,"isAutoPay":0,"availables":0,"paid":0,"isChapterPaid":0,"showLectureButton":1,"wxtts":1,"star":86,"ratingCount":7704,"ratingDetail":{"one":60,"two":81,"three":672,"four":2099,"five":4751,"recent":116},"newRating":760,"newRatingCount":6997,"newRatingDetail":{"good":5316,"fair":1633,"poor":48,"recent":116,"myRating":"","title":"值得一读"},"copyrightInfo":{"id":2000000324,"name":"博集新媒","userVid":384737583},"authorSeg":[{"words":"桦泽紫苑","highlight":1}]}