{"bookId":"22739878","title":"高维度思考法","author":"细谷功","cover":"https://wfqqreader-1252317822.image.myqcloud.com/cover/878/22739878/s_22739878.jpg","version":1627173306,"format":"epub","type":0,"price":22.80,"originalPrice":0,"soldout":0,"bookStatus":1,"payType":4097,"finished":1,"maxFreeChapter":6,"free":0,"mcardDiscount":0,"ispub":1,"cpid":2000000226,"centPrice":2280,"category":"个人成长榜-人生哲学","hasLecture":0,"intro":"本书以伊索寓言中的“蚂蚁和蝈蝈”来做比喻，分析“解决问题型”和“发现问题型”这两种思考方式的不同和特征。指出擅长解决既有问题的人并不擅长发现问题，反之亦然。但是这二者在企业中同时存在，掌握发现问题的思考方式，自觉认识到自己原本在哪些部分上占优势，思考如何活用自己的长处，克服自己的短处，才是最关键的。同时，为了更好地在未知领域中发现问题，书中还介绍了三种提升视角或思考“维度”的方法，让大家更好地发现问题，正确定义问题，从而做到真正的问题解决。","lastChapterIdx":23,"paperBook":{"skuId":"12342941"},"chapterSize":23,"updateTime":1618351259,"onTime":1534908083,"unitPrice":0.05,"marketType":0,"isbn":"9787511376336","publisher":"中国华侨出版社","publishTime":"2018-06-01 00:00:00","totalWords":93064,"publishPrice":38.00,"bookSize":435855,"recommended":0,"lectureRecommended":0,"follow":0,"secret":0,"offline":0,"lectureOffline":0,"finishReading":0,"isAutoPay":0,"availables":0,"paid":0,"isChapterPaid":0,"showLectureButton":1,"wxtts":1,"star":82,"ratingCount":371,"ratingDetail":{"one":8,"two":13,"three":40,"four":86,"five":220,"recent":1},"newRating":700,"newRatingCount":323,"newRatingDetail":{"good":226,"fair":89,"poor":8,"recent":1,"myRating":"","title":""},"copyrightInfo":{"id":2000000226,"name":"后浪出版","userVid":23226616},"authorSeg":[{"words":"细谷功","highlight":1}]}