{"bookId":"22902874","title":"英国史Ⅰ：在世界的边缘？（3000BC-AD1603）","author":"西蒙·沙玛","cover":"https://wfqqreader-1252317822.image.myqcloud.com/cover/874/22902874/s_22902874.jpg","version":1058657912,"format":"epub","type":0,"price":47.60,"originalPrice":0,"soldout":0,"bookStatus":1,"payType":4097,"finished":1,"maxFreeChapter":5,"free":0,"mcardDiscount":0,"ispub":1,"cpid":2000000231,"centPrice":4760,"category":"历史榜-世界史","hasLecture":0,"intro":"《英国史Ⅰ：在世界的边缘？（3000BC-AD1603）》包括超过1500年的英国历史，从罗马第一次入侵到伊丽莎白女王非凡的统治时期。本书的视角从文明诞生开始，到诺曼征服，从宗教战争、黑暗的中世纪到亨利二世的国家风波；黑死病的爆发，几乎毁了半个欧洲的人口，都铎王朝错综复杂的矛盾，伊丽莎白一世和苏格兰玛丽女王之间的冲突构成了本卷的主要内容。通过故事本身探索相互关联的主题网络——一个民族国家的形成究竟是因何形成，压迫者和被压迫者之间的斗争，历史内在推动的力量都在期间可见一斑。","lastChapterIdx":13,"paperBook":{"skuId":""},"chapterSize":13,"updateTime":1618364791,"onTime":1535527966,"unitPrice":0.05,"marketType":0,"isbn":"","publisher":"中信出版社","publishTime":"2018-07-01 00:00:00","totalWords":272247,"publishPrice":79.30,"bookSize":1056722,"recommended":0,"lectureRecommended":0,"follow":0,"secret":0,"offline":0,"lectureOffline":0,"finishReading":0,"isAutoPay":0,"availables":0,"paid":0,"isChapterPaid":0,"showLectureButton":1,"wxtts":1,"star":79,"ratingCount":86,"ratingDetail":{"one":4,"two":2,"three":12,"four":25,"five":43,"recent":3},"newRating":663,"newRatingCount":80,"newRatingDetail":{"good":53,"fair":24,"poor":3,"recent":3,"myRating":"","title":""},"copyrightInfo":{"id":2000000231,"name":"中信出版集团","userVid":168010251},"authorSeg":[{"words":"西蒙·沙玛","highlight":1}]}