{"bookId":"23514477","title":"写作提高一点点","author":"玛丽-凯特·麦基","cover":"https://wfqqreader-1252317822.image.myqcloud.com/cover/477/23514477/s_23514477.jpg","version":394295370,"format":"epub","type":0,"price":27.00,"originalPrice":0,"soldout":0,"bookStatus":1,"payType":4097,"finished":1,"maxFreeChapter":7,"free":0,"mcardDiscount":0,"ispub":1,"cpid":2000000231,"centPrice":2700,"category":"文学榜-语言文字","hasLecture":0,"intro":"不管你从事的是何种职业，基本都会涉及写作，哪怕这并不是你的工作职责。但对于一些不喜欢写作的人而言，恐怕连写一封最简单的电子邮件也会成为一个难题。这本书是一个跳板，能帮助你应对任何需要写作技能的工作、感兴趣的项目和情况。无论你要写的是博客、演讲稿、公号文章，还是新闻稿件，甚至留言条，这本分步指南都能为你提供完成任务所需要的各类实用技巧。这本书能让你明确自己的写作问题出在哪里，帮助你选择快捷、合适的补救方法。现在，你就可以用它来提升自己的写作技能。","lastChapterIdx":20,"paperBook":{"skuId":"12452896"},"chapterSize":20,"updateTime":1618437183,"onTime":1543285491,"unitPrice":0.05,"marketType":0,"isbn":"9787508692333","publisher":"中信出版社","publishTime":"2018-09-01 00:00:00","totalWords":113583,"publishPrice":45.00,"bookSize":540343,"recommended":0,"lectureRecommended":0,"follow":0,"secret":0,"offline":0,"lectureOffline":0,"finishReading":0,"isAutoPay":0,"availables":0,"paid":0,"isChapterPaid":0,"showLectureButton":1,"wxtts":1,"star":82,"ratingCount":222,"ratingDetail":{"one":3,"two":6,"three":22,"four":57,"five":133,"recent":2},"newRating":724,"newRatingCount":181,"newRatingDetail":{"good":131,"fair":48,"poor":2,"recent":2,"myRating":"","title":""},"copyrightInfo":{"id":2000000231,"name":"中信出版集团","userVid":168010251},"authorSeg":[{"words":"玛丽-凯特·麦基","highlight":1}]}