{"bookId":"23774475","title":"曾国藩传","author":"张宏杰","cover":"https://wfqqreader-1252317822.image.myqcloud.com/cover/475/23774475/s_23774475.jpg","version":575327694,"format":"epub","type":0,"price":34.00,"originalPrice":0,"soldout":0,"bookStatus":1,"payType":1048577,"finished":1,"maxFreeChapter":7,"free":0,"mcardDiscount":0,"ispub":1,"cpid":60041,"centPrice":3400,"category":"传记榜-历史人物","authorVids":"18667618","hasLecture":1,"intro":"曾国藩，没有显赫的家世，天赋堪称晚清同时代大人物当中最差，却官至两江总督、直隶总督、武英殿大学士，在复杂的时代变局中超越众人，成就最大，被誉为大清“中兴第一名臣”，且最后全身而退。他的人生经历，无论是过去还是现在都给人以特别的启示。","lastChapterIdx":24,"paperBook":{"skuId":"12469371"},"chapterSize":24,"updateTime":1618488104,"onTime":1546854973,"unitPrice":0.05,"marketType":0,"isbn":"9787513921091","publisher":"民主与建设出版社","publishTime":"2018-12-01 00:00:00","totalWords":277820,"publishPrice":68.00,"bookSize":3435140,"recommended":0,"lectureRecommended":0,"follow":0,"secret":0,"offline":0,"lectureOffline":0,"finishReading":0,"isAutoPay":0,"availables":0,"paid":0,"isChapterPaid":0,"showLectureButton":1,"wxtts":1,"star":89,"ratingCount":23703,"ratingDetail":{"one":265,"two":147,"three":631,"four":3895,"five":18672,"recent":164},"newRating":865,"newRatingCount":20488,"newRatingDetail":{"good":17724,"fair":2563,"poor":201,"recent":150,"myRating":"","title":"好评如潮"},"ranklist":{"seq":34,"categoryId":"all","categoryName":"总榜","storeSubType":0,"scheme":"weread://ranklist?categoryId=all&subtype=0&initialBookId=23774475&seq=34","ranklistCover":{"tinycode":"https://rescdn.qqmail.com/weread/cover/ranklist.all.tinycode.8A3kIWv1MX.png","chart_title":"https://rescdn.qqmail.com/weread/cover/ranklist.all.chart_title.Ck2o3M5aVF.png","chart_detail_title":"https://weread-1258476243.file.myqcloud.com/assets/ranklist.all.chart_detail_title.sMh65ixe9l.png","chart_detail_title_dark":"https://weread-1258476243.file.myqcloud.com/assets/ranklist.all.chart_detail_title_dark.2ky4HSJU3V.png","chart_share_title":"https://rescdn.qqmail.com/weread/cover/ranklist.all.chart_share_title.hqPEOLVffW.png","chart_share_logo":"https://rescdn.qqmail.com/weread/cover/ranklist.all.chart_share_logo.8DDUxHqsiv.png","chart_book_detial_icon":"https://rescdn.qqmail.com/weread/cover/ranklist.all.chart_book_detial_icon.6tpmPfmz6F.png","chart_tag":"https://weread-1258476243.file.myqcloud.com/assets/ranklist.all.chart_tag.9KOzos3kWl.png","eink_chart_title":"https://weread-1258476243.file.myqcloud.com/assets/ranklist.all.eink_chart_title.ongSx5S5qo.png","chart_title_main":"https://weread-1258476243.file.myqcloud.com/assets/ranklist.all.chart_title_main.5y2PAdJQdr.png","chart_detail_title_main":"https://weread-1258476243.file.myqcloud.com/assets/ranklist.all.chart_detail_title_main.VC1GJeqgCf.png","chart_detail_title_dark_main":"https://weread-1258476243.file.myqcloud.com/assets/ranklist.all.chart_detail_title_dark_main.r45lFTyRNo.png","chart_background_color_1":"#D4B778","chart_background_color_2":"#DBC79C","chart_title_height":96,"chart_title_width":471}},"copyrightInfo":{"id":60041,"name":"磨铁数盟","userVid":351681843},"authorSeg":[{"words":"张宏杰","highlight":1}]}