{"bookId":"3000013128","title":"身心合一的奇迹力量","author":"提摩西加尔韦 ","cover":"https://res.weread.qq.com/extcover/600398845","version":0,"format":"txt","type":0,"price":-1,"originalPrice":0,"soldout":1,"bookStatus":5,"payType":0,"finished":1,"maxFreeChapter":0,"free":0,"mcardDiscount":0,"ispub":1,"cpid":0,"centPrice":-1,"hasLecture":0,"intro":"《身心合一的奇迹力量》讲述在高水平的比赛中，双方都是高手，旗鼓相当，是什么因素决定谁最终获胜呢？美国运动心理学第一人、教练技术的先驱提摩西加尔韦，30年来致力于探索体坛顶尖选手最终制胜的心理秘密。他发现，赛场上的选手在进行激烈的外在比赛时，内心还进行着一场内在比赛，内在比赛要克服的目标，就是心中的负面心理习惯，正是这些习惯让选手与胜利失之交臂。心魔才是取胜最大的障碍。要想赢得比赛，秘诀就是不要过于执念，如果选手能够克服内在障碍，身心合一，就会产生真正的求胜欲望，释放出全部能量，实现惊人的突破。提摩西加尔韦据此发展出一整套赢得内在比赛的诀窍。《身心合一的奇迹力量》不仅适合教练员、运动员，更适合那些希望在人生中不断获得突破和成长的人们。","lastChapterIdx":55,"paperBook":{"skuId":""},"chapterSize":55,"updateTime":0,"unitPrice":0,"marketType":0,"isbn":"9787508073231","publisher":"","publishTime":"","totalWords":0,"recommended":0,"lectureRecommended":0,"follow":0,"secret":0,"offline":0,"lectureOffline":0,"finishReading":0,"isAutoPay":0,"availables":0,"paid":0,"isChapterPaid":0,"showLectureButton":0,"wxtts":1,"subscribeCount":10180,"subscribeSeq":0,"star":82,"ratingCount":126,"ratingDetail":{"one":5,"two":1,"three":0,"four":10,"five":110,"recent":1},"newRating":922,"newRatingCount":115,"newRatingDetail":{"good":106,"fair":6,"poor":3,"recent":1,"myRating":"","title":""},"authorSeg":[{"words":"提摩西加尔韦","highlight":1},{"words":" ","highlight":0}]}