{"bookId":"3000071015","title":"梦梁录","author":"吴自牧/张社国/符均","cover":"https://res.weread.qq.com/extcover/600498298","version":0,"format":"txt","type":0,"price":-1,"originalPrice":0,"soldout":1,"bookStatus":5,"payType":0,"finished":1,"maxFreeChapter":0,"free":0,"mcardDiscount":0,"ispub":1,"cpid":0,"centPrice":-1,"hasLecture":0,"intro":"《梦梁录》南宋吴自牧著。成书于南宋末年，叙述整个南宋时期的临安(今浙江杭州)情况，而尤详于淳 至咸淳之间(1241—1274)，其中记录了不少关于民俗和民艺的材料。","lastChapterIdx":0,"paperBook":{"skuId":""},"chapterSize":0,"updateTime":0,"unitPrice":0,"marketType":0,"isbn":"9787806288207","publisher":"","publishTime":"","totalWords":0,"recommended":0,"lectureRecommended":0,"follow":0,"secret":0,"offline":0,"lectureOffline":0,"finishReading":0,"isAutoPay":0,"availables":0,"paid":0,"isChapterPaid":0,"showLectureButton":0,"wxtts":1,"subscribeCount":1490,"subscribeSeq":0,"ratingCount":11,"ratingDetail":{"one":0,"two":1,"three":0,"four":2,"five":8,"recent":0},"newRating":0,"newRatingCount":9,"newRatingDetail":{"good":8,"fair":1,"poor":0,"recent":0,"myRating":"","title":"评分不足"},"authorSeg":[{"words":"吴自牧","highlight":1},{"words":"/","highlight":0},{"words":"张社国","highlight":1},{"words":"/","highlight":0},{"words":"符均","highlight":1}]}