{"bookId":"34919601","title":"曾奇峰的心理课","author":"曾奇峰","cover":"https://wfqqreader-1252317822.image.myqcloud.com/cover/601/34919601/s_34919601.jpg","version":0,"format":"txt","type":0,"price":31.20,"originalPrice":0,"soldout":0,"bookStatus":1,"payType":4097,"finished":1,"maxFreeChapter":4,"free":0,"mcardDiscount":0,"ispub":1,"cpid":60041,"centPrice":3120,"category":"心理榜-心理学研究","hasLecture":0,"intro":"精神分析，是一门真正意义上的成功学。人生最大的成功，莫过于充分地成为自己，拥有健康和强大的人格。精神分析可以帮助我们解放被压抑和扭曲的人格，获得真正意义上的自由。本书应用4大生活场景，覆盖自我认知+关系洞察+情绪管理+科学育儿；囊括精神分析核心理念，针对性解决生活中的最重要议题，为你写下治愈心灵的药方；系统讲解心理咨询真实操作流程，是送给每一位咨询师和来访者的心理自助手册。","lastChapterIdx":11,"paperBook":{"skuId":"12753815"},"chapterSize":11,"updateTime":1606698734,"onTime":1606698731,"unitPrice":0.05,"marketType":0,"isbn":"9787505750098","publisher":"中国友谊出版公司","publishTime":"2020-11-26 00:00:00","totalWords":102412,"publishPrice":52.00,"recommended":0,"lectureRecommended":0,"follow":0,"secret":0,"offline":0,"lectureOffline":0,"finishReading":0,"isAutoPay":0,"availables":0,"paid":0,"isChapterPaid":0,"showLectureButton":1,"wxtts":1,"star":85,"ratingCount":296,"ratingDetail":{"one":10,"two":0,"three":36,"four":10,"five":240,"recent":29},"newRating":835,"newRatingCount":273,"newRatingDetail":{"good":228,"fair":37,"poor":8,"recent":28,"myRating":"","title":""},"copyrightInfo":{"id":60041,"name":"磨铁数盟","userVid":351681843},"authorSeg":[{"words":"曾奇峰","highlight":1}]}