{"bookId":"522374","title":"伤寒论（四库全书）","author":"陈仁寿","cover":"https://wfqqreader-1252317822.image.myqcloud.com/cover/374/522374/s_522374.jpg","version":0,"format":"txt","type":0,"price":1.99,"originalPrice":0,"soldout":0,"bookStatus":1,"payType":4097,"finished":1,"maxFreeChapter":6,"free":0,"mcardDiscount":0,"ispub":1,"cpid":3401069,"centPrice":199,"category":"历史榜-历史典籍","hasLecture":1,"intro":"    在中国医学史上，东汉张仲景的《伤寒论》可以称得上是时代的著作。中国医学的肇始期可上溯几千年，至此，才理法方药大僃，为医学的发展奠定了坚实的基础，并因其滋养，产生了精彩纷呈的各种医学流派。《伤寒论》篇什不过十卷，然包罗宏富，精微玄妙，常读常新，帮后世彦各骋其智，祖述推演以探求仲景深意者，层出不穷，著述不下数十百家，为杏林增色不少。本书对《伤寒论》进行了全面的点校，内容分为三个部分：伤寒论注释、伤寒明理论、伤寒论方。","lastChapterIdx":13,"paperBook":{"skuId":""},"chapterSize":13,"updateTime":1581688366,"onTime":1439282473,"unitPrice":0.05,"marketType":0,"isbn":"9787534557316","publisher":"江苏科学技术出版社","publishTime":"2008-01-01 00:00:00","totalWords":153741,"publishPrice":20.00,"recommended":0,"lectureRecommended":0,"follow":0,"secret":0,"offline":0,"lectureOffline":0,"finishReading":0,"isAutoPay":0,"availables":0,"paid":0,"isChapterPaid":0,"showLectureButton":1,"wxtts":1,"star":86,"ratingCount":336,"ratingDetail":{"one":9,"two":4,"three":11,"four":16,"five":279,"recent":1},"newRating":876,"newRatingCount":258,"newRatingDetail":{"good":226,"fair":23,"poor":9,"recent":0,"myRating":"","title":""},"copyrightInfo":{"id":3401069,"name":"凤凰科技出版社","userVid":0},"authorSeg":[{"words":"陈仁寿","highlight":1}]}