{"bookId":"610507","title":"孙思邈与千金方","author":"金开诚主编","cover":"https://wfqqreader-1252317822.image.myqcloud.com/cover/507/610507/s_610507.jpg","version":0,"format":"txt","type":0,"price":0.99,"originalPrice":0,"soldout":0,"bookStatus":1,"payType":4097,"finished":1,"maxFreeChapter":3,"free":0,"mcardDiscount":0,"ispub":1,"cpid":2000000029,"centPrice":99,"category":"医学健康榜-医学","hasLecture":0,"intro":"中国文化知识读本：孙思邈与》介绍了孙思邈与《千金方》的有关内容。《孙思邈与》中优美生动的文字、简明通俗的语言、图文并茂的形式，把中国文化中的物态文化、制度文化、行为文化、精神文化等知识要点全面展示给读者。点点滴滴的文化知识仿佛颗颗繁星，组成了灿烂辉煌的中国文化的天穹。能为弘扬中华五千年优秀传统文化、增强各民族团结、构建社会主义和谐社会尽一份绵薄之力。","lastChapterIdx":7,"paperBook":{"skuId":""},"chapterSize":7,"updateTime":1581653551,"onTime":1432790126,"unitPrice":0.05,"marketType":0,"isbn":"9787546339689","publisher":"吉林文史出版社","publishTime":"2011-01-01 00:00:00","totalWords":27790,"publishPrice":14.80,"recommended":0,"lectureRecommended":0,"follow":0,"secret":0,"offline":0,"lectureOffline":0,"finishReading":0,"isAutoPay":0,"availables":0,"paid":0,"isChapterPaid":0,"showLectureButton":1,"wxtts":1,"star":80,"ratingCount":146,"ratingDetail":{"one":6,"two":3,"three":11,"four":19,"five":99,"recent":6},"newRating":764,"newRatingCount":127,"newRatingDetail":{"good":97,"fair":24,"poor":6,"recent":3,"myRating":"","title":""},"copyrightInfo":{"id":2000000029,"name":"吉林文史出版社","userVid":0},"authorSeg":[{"words":"金开诚","highlight":1},{"words":"主编","highlight":0}]}