{"bookId":"699603","title":"老人与海","author":"海明威","cover":"https://wfqqreader-1252317822.image.myqcloud.com/cover/603/699603/s_699603.jpg","version":0,"format":"txt","type":0,"price":2.18,"originalPrice":0,"soldout":0,"bookStatus":1,"payType":4097,"finished":1,"maxFreeChapter":2,"free":0,"mcardDiscount":0,"ispub":1,"cpid":2000000145,"centPrice":218,"category":"精品小说榜-世界名著","hasLecture":1,"intro":"    《老人与海》是海明威于1951年在古巴写的一篇中篇小说，于1952年出版。是海明威最著名的作品之一。它围绕一位老年古巴渔夫，与一条巨大的马林鱼在离岸很远的湾流中搏斗而展开故事的讲述。它奠定了海明威在世界文学中的突出地位，这篇小说相继获得了1953年美国普利策奖和1954年诺贝尔文学奖。","lastChapterIdx":11,"paperBook":{"skuId":""},"chapterSize":11,"updateTime":1581648059,"onTime":1452672596,"unitPrice":0.05,"marketType":0,"isbn":"9787800948985","publisher":"大众文艺出版社","publishTime":"2000-08-01 00:00:00","totalWords":209496,"publishPrice":18.00,"recommended":0,"lectureRecommended":0,"follow":0,"secret":0,"offline":0,"lectureOffline":0,"finishReading":0,"isAutoPay":0,"availables":0,"paid":0,"isChapterPaid":0,"showLectureButton":1,"wxtts":1,"star":86,"ratingCount":6933,"ratingDetail":{"one":198,"two":110,"three":532,"four":1208,"five":4619,"recent":82},"newRating":773,"newRatingCount":6050,"newRatingDetail":{"good":4674,"fair":1223,"poor":153,"recent":72,"myRating":"","title":"值得一读"},"copyrightInfo":{"id":2000000145,"name":"青苹果数据中心","userVid":0},"authorSeg":[{"words":"海明威","highlight":1}]}