{"bookId":"714305","title":"从晚清到民国","author":"唐德刚","cover":"https://wfqqreader-1252317822.image.myqcloud.com/cover/305/714305/s_714305.jpg","version":0,"format":"txt","type":0,"price":17.99,"originalPrice":0,"soldout":0,"bookStatus":1,"payType":4097,"finished":1,"maxFreeChapter":4,"free":0,"mcardDiscount":0,"ispub":1,"cpid":2000000324,"centPrice":1799,"category":"历史榜-中国史","hasLecture":1,"intro":"    长江三峡的曲折动荡，是中国人的骄傲，也是中国自然史上的潮信地带。鸦片战争，揭开了中国二千年一遇的“社会文化大转型”的序幕。在史学大家唐德刚的慧眼中，“人文史观”一如“自然史观”，1840年的一场战役不仅掀起了中国社会政治形态的大变革，也使历史潮流中的长河，尤需历时百年的诡谲动荡，方能进入壮阔的太平洋。唐德刚交融三峡史观与人文探索于本书，成就一部客观而深入的中国近代史书。","lastChapterIdx":7,"paperBook":{"skuId":"12763244"},"chapterSize":7,"updateTime":1581650800,"onTime":1444700941,"unitPrice":0.05,"marketType":0,"isbn":"9787503462252","publisher":"中国文史出版社","publishTime":"2015-06-01 00:00:00","totalWords":289695,"publishPrice":50.00,"recommended":0,"lectureRecommended":0,"follow":0,"secret":0,"offline":0,"lectureOffline":0,"finishReading":0,"isAutoPay":0,"availables":0,"paid":0,"isChapterPaid":0,"showLectureButton":1,"wxtts":1,"star":85,"ratingCount":3373,"ratingDetail":{"one":84,"two":44,"three":194,"four":719,"five":2046,"recent":10},"newRating":773,"newRatingCount":2682,"newRatingDetail":{"good":2074,"fair":546,"poor":62,"recent":10,"myRating":"","title":"值得一读"},"copyrightInfo":{"id":2000000324,"name":"博集新媒","userVid":384737583},"authorSeg":[{"words":"唐德刚","highlight":1}]}