{"bookId":"728523","title":"葬礼之后","author":"阿加莎·克里斯蒂","cover":"https://wfqqreader-1252317822.image.myqcloud.com/cover/523/728523/s_728523.jpg","version":0,"format":"txt","type":0,"price":22.99,"originalPrice":0,"soldout":0,"bookStatus":1,"payType":4097,"finished":1,"maxFreeChapter":5,"free":0,"mcardDiscount":0,"ispub":1,"cpid":36739,"centPrice":2299,"category":"精品小说榜-悬疑推理","hasLecture":0,"intro":"    理查德·阿伯内西在死前留下了一大笔财产。在他的葬礼之后，他的妹妹、行为举止总是颇为奇怪的科拉小姐竟说了这样的话——“可他是被谋杀的，不是吗？”次日，科拉在家中的床上惨遭杀害。六个遗产受益人均有作案动机，每个人都恰巧没有不在场证明！这桩“有趣”的案件令波洛陷入窘境……他能否从和家族成员的对话中抽丝剥茧并发现蛛丝马迹？迷雾重重，真相直到故事最后才被揭开！","lastChapterIdx":41,"paperBook":{"skuId":"11598693"},"chapterSize":41,"updateTime":1594795112,"onTime":1445479984,"unitPrice":0.05,"marketType":0,"isbn":"9787513316972","publisher":"新星出版社","publishTime":"2014-12-01 00:00:00","totalWords":133357,"publishPrice":28.00,"recommended":0,"lectureRecommended":0,"follow":0,"secret":0,"offline":0,"lectureOffline":0,"finishReading":0,"isAutoPay":0,"availables":0,"paid":0,"isChapterPaid":0,"showLectureButton":1,"wxtts":1,"star":83,"ratingCount":638,"ratingDetail":{"one":1,"two":3,"three":66,"four":205,"five":338,"recent":7},"newRating":747,"newRatingCount":593,"newRatingDetail":{"good":443,"fair":149,"poor":1,"recent":7,"myRating":"","title":"值得一读"},"copyrightInfo":{"id":36739,"name":"新星出版社","userVid":124395018},"authorSeg":[{"words":"阿加莎·克里斯蒂","highlight":1}]}