{"bookId":"754056","title":"人间椅子","author":"江户川乱步","cover":"https://wfqqreader-1252317822.image.myqcloud.com/cover/56/754056/s_754056.jpg","version":0,"format":"txt","type":0,"price":15.99,"originalPrice":0,"soldout":0,"bookStatus":1,"payType":4097,"finished":1,"maxFreeChapter":2,"free":0,"mcardDiscount":0,"ispub":1,"cpid":36739,"centPrice":1599,"category":"精品小说榜-悬疑推理","hasLecture":0,"intro":"一位有名的女作家，收到一个沉甸甸的信封，打开看到一封很厚的书信。内容是一名椅子工匠的告白，他说曾经躲进亲自制作的豪华椅子里，最初被送到饭店，观察并接触各式各样的人，几个月后椅子易主，变为一位富裕的外交官座椅，其夫人是有名的作家，工匠爱上了作家……是一篇异想天开的猎奇小说杰作。《人间椅子》为《江户川乱步作品集》第三卷。一共收录江户川乱步所撰写的变格推理短篇十五篇。《人间椅子》是乱步的第二十一则短篇。","lastChapterIdx":19,"paperBook":{"skuId":""},"chapterSize":19,"updateTime":1594795109,"onTime":1448590372,"unitPrice":0.05,"marketType":0,"isbn":"9787513303293","publisher":"新星出版社","publishTime":"2011-07-01 00:00:00","totalWords":142271,"publishPrice":28.00,"recommended":0,"lectureRecommended":0,"follow":0,"secret":0,"offline":0,"lectureOffline":0,"finishReading":0,"isAutoPay":0,"availables":0,"paid":0,"isChapterPaid":0,"showLectureButton":1,"wxtts":1,"star":85,"ratingCount":2372,"ratingDetail":{"one":21,"two":23,"three":250,"four":742,"five":1306,"recent":61},"newRating":738,"newRatingCount":2233,"newRatingDetail":{"good":1649,"fair":567,"poor":17,"recent":61,"myRating":"","title":"值得一读"},"copyrightInfo":{"id":36739,"name":"新星出版社","userVid":124395018},"authorSeg":[{"words":"江户川乱步","highlight":1}]}