{"bookId":"758867","title":"1984","author":"乔治·奥威尔","cover":"https://wfqqreader-1252317822.image.myqcloud.com/cover/867/758867/s_758867.jpg","version":0,"format":"txt","type":0,"price":6.00,"originalPrice":0,"soldout":0,"bookStatus":1,"payType":4097,"finished":1,"maxFreeChapter":4,"free":0,"mcardDiscount":0,"ispub":1,"cpid":2000000244,"centPrice":600,"category":"精品小说榜-社会小说","hasLecture":1,"intro":"    《1984》是一部伟大的政治寓言。1984年的世界被三个超级大国瓜分，三个国家之间战争不断，国家内部社会结构被彻底打破，均实行高度集权统治，以改变历史、改变语言、打破家庭等极端手段钳制人们的思想和本能，并用高科技手段监视控制人们的行为，以对领袖的个人崇拜和对国内外敌人的仇恨维持社会的运转。","lastChapterIdx":41,"paperBook":{"skuId":""},"chapterSize":41,"updateTime":1583302944,"onTime":1451287637,"unitPrice":0.05,"marketType":0,"isbn":"9787544741835","publisher":"译林出版社","publishTime":"2013-10-01 00:00:00","totalWords":189407,"publishPrice":25.00,"recommended":0,"lectureRecommended":0,"follow":0,"secret":0,"offline":0,"lectureOffline":0,"finishReading":0,"isAutoPay":0,"availables":0,"paid":0,"isChapterPaid":0,"showLectureButton":1,"wxtts":1,"star":89,"ratingCount":4646,"ratingDetail":{"one":28,"two":11,"three":211,"four":742,"five":3474,"recent":209},"newRating":849,"newRatingCount":3986,"newRatingDetail":{"good":3386,"fair":577,"poor":23,"recent":192,"myRating":"","title":"脍炙人口"},"ranklist":{"seq":94,"categoryId":"all","categoryName":"总榜","storeSubType":0,"scheme":"weread://ranklist?categoryId=all&subtype=0&initialBookId=758867&seq=94","ranklistCover":{"tinycode":"https://rescdn.qqmail.com/weread/cover/ranklist.all.tinycode.8A3kIWv1MX.png","chart_title":"https://rescdn.qqmail.com/weread/cover/ranklist.all.chart_title.Ck2o3M5aVF.png","chart_detail_title":"https://weread-1258476243.file.myqcloud.com/assets/ranklist.all.chart_detail_title.sMh65ixe9l.png","chart_detail_title_dark":"https://weread-1258476243.file.myqcloud.com/assets/ranklist.all.chart_detail_title_dark.2ky4HSJU3V.png","chart_share_title":"https://rescdn.qqmail.com/weread/cover/ranklist.all.chart_share_title.hqPEOLVffW.png","chart_share_logo":"https://rescdn.qqmail.com/weread/cover/ranklist.all.chart_share_logo.8DDUxHqsiv.png","chart_book_detial_icon":"https://rescdn.qqmail.com/weread/cover/ranklist.all.chart_book_detial_icon.6tpmPfmz6F.png","chart_tag":"https://weread-1258476243.file.myqcloud.com/assets/ranklist.all.chart_tag.9KOzos3kWl.png","eink_chart_title":"https://weread-1258476243.file.myqcloud.com/assets/ranklist.all.eink_chart_title.ongSx5S5qo.png","chart_title_main":"https://weread-1258476243.file.myqcloud.com/assets/ranklist.all.chart_title_main.5y2PAdJQdr.png","chart_detail_title_main":"https://weread-1258476243.file.myqcloud.com/assets/ranklist.all.chart_detail_title_main.VC1GJeqgCf.png","chart_detail_title_dark_main":"https://weread-1258476243.file.myqcloud.com/assets/ranklist.all.chart_detail_title_dark_main.r45lFTyRNo.png","chart_background_color_1":"#D4B778","chart_background_color_2":"#DBC79C","chart_title_height":96,"chart_title_width":471}},"copyrightInfo":{"id":2000000244,"name":"译林出版社","userVid":309077157},"authorSeg":[{"words":"乔治·奥威尔","highlight":1}]}