{"bookId":"791807","title":"人面桃花","author":"格非","cover":"http://wfqqreader-1252317822.image.myqcloud.com/cover/807/791807/s_791807.jpg","version":0,"format":"txt","type":0,"price":12.00,"originalPrice":0,"soldout":1,"bookStatus":1,"payType":524289,"finished":1,"maxFreeChapter":2,"free":0,"mcardDiscount":0,"ispub":1,"cpid":2000000708,"centPrice":1200,"category":"精品小说榜-社会小说","hasLecture":0,"intro":"    本书是著名作家格非集十年心血完成的一部精致的小说，作者的功力直抵小说细部的每一个末梢，真可谓一丝不苟。它既是格非蜕变和超越的一次个人记录，同时也可视为是当代作家制造经典的有效标志，从阅读角度说人面桃花是一部让人舍不得一口气读完的小说。看过这样的小说，相信你大概会明白好的小说与差的小说、好的作家与差的作家区别在哪里。小说讲述晚清末年、民国初年江南官宦小姐陆秀米与时代梦想、社会剧变相互纠缠的传奇人生。","lastChapterIdx":5,"paperBook":{"skuId":""},"chapterSize":5,"updateTime":1527840921,"onTime":1453977045,"unitPrice":0.05,"marketType":0,"isbn":"9787532144020","publisher":"上海文艺出版社","publishTime":"","totalWords":193585,"publishPrice":30.00,"recommended":0,"lectureRecommended":0,"follow":0,"secret":0,"offline":0,"lectureOffline":0,"finishReading":0,"isAutoPay":0,"availables":0,"paid":0,"isChapterPaid":0,"showLectureButton":1,"wxtts":1,"subscribeCount":2404,"subscribeSeq":0,"star":79,"ratingCount":1567,"ratingDetail":{"one":4,"two":18,"three":110,"four":418,"five":759,"recent":2},"newRating":763,"newRatingCount":1258,"newRatingDetail":{"good":960,"fair":294,"poor":4,"recent":2,"myRating":"","title":"值得一读"},"copyrightInfo":{"id":2000000708,"name":"中作华文","userVid":0},"authorSeg":[{"words":"格非","highlight":1}]}