{"bookId":"812819","title":"从零开始做运营","author":"张亮","cover":"https://wfqqreader-1252317822.image.myqcloud.com/cover/819/812819/s_812819.jpg","version":1830677776,"format":"epub","type":0,"price":4.99,"originalPrice":0,"soldout":0,"bookStatus":1,"payType":4097,"finished":1,"maxFreeChapter":14,"free":0,"mcardDiscount":0,"ispub":1,"cpid":2000000231,"centPrice":499,"category":"经济理财榜-商业","authorVids":"10913008","hasLecture":1,"intro":"运营是什么？怎样做运营？产品和运营是什么关系？我是否适合从事互联网运营？《从零开始做运营》涵盖了互联网运营的精髓与核心内容，从运营是什么讲起，涉及内容运营、用户运营、活动运营、数据分析等多个方面，涵盖互联网运营的全部环节，张亮结合自身经验，讨论了大量经典运营案例，以便读者更好地掌握运营的精神。 除了为互联网运营人员提供有关全面而科学的运营知识与案例，《从零开始做运营》也为那些徘徊于互联网行业大门外的年轻人指明方向，在互联网大热的今天，互联网运营成为一个越来越重要的岗位。很多年轻人带着对互联网的热情投身到这个行业，却发现自己对这个行业所知甚少，对互联网运营更加陌生，甚至有一些有志于从事互联网运营的人，因为对其缺乏了解而难以确定职业发展方向，《从零开始做运营》将为他们开启一扇从学校到社会、从入门到入行的窗。 通过《从零开始做运营》，你可以全面了解运营工作的范围、职责、核心，确立科学的运营观念和思路，掌握精妙的运营技巧与策略，并更好地规划职业发展方向。读了这本《从零开始做运营》，你将不再是一个运营新手，而是一个拥有成熟的运营逻辑体系的运营人。","lastChapterIdx":49,"paperBook":{"skuId":"11825266"},"chapterSize":49,"updateTime":1618921055,"onTime":1458037216,"unitPrice":0.05,"marketType":0,"isbn":"9787508655659","publisher":"中信出版社","publishTime":"2015-12-01 00:00:00","totalWords":132724,"publishPrice":49.00,"bookSize":991484,"recommended":0,"lectureRecommended":0,"follow":0,"secret":0,"offline":0,"lectureOffline":0,"finishReading":0,"isAutoPay":0,"availables":0,"paid":0,"isChapterPaid":0,"showLectureButton":1,"wxtts":1,"star":84,"ratingCount":4911,"ratingDetail":{"one":59,"two":64,"three":459,"four":1324,"five":2517,"recent":17},"newRating":734,"newRatingCount":4138,"newRatingDetail":{"good":3038,"fair":1050,"poor":50,"recent":17,"myRating":"","title":"值得一读"},"copyrightInfo":{"id":2000000231,"name":"中信出版集团","userVid":168010251},"authorSeg":[{"words":"张亮","highlight":1}]}