{"bookId":"846523","title":"牛津通识读本：叔本华（中文版）","author":"克里斯托弗·贾纳韦","cover":"https://wfqqreader-1252317822.image.myqcloud.com/cover/523/846523/s_846523.jpg","version":615944501,"format":"epub","type":0,"price":10.00,"originalPrice":0,"soldout":0,"bookStatus":1,"payType":4097,"finished":1,"maxFreeChapter":6,"free":0,"mcardDiscount":0,"ispub":1,"cpid":2000000244,"centPrice":1000,"category":"哲学宗教榜-西方哲学","hasLecture":0,"intro":"德国哲学家当中，叔本华是最有可读性的一位。本书对叔本华的形而上学哲学体系进行了简洁的阐释，尤其聚焦于叔本华思想的原创性特征，这种原创性启发了包括尼采、瓦格纳、弗洛伊德、维特根斯坦等在内的许多艺术家和思想家。作者将笔锋直接指向叔本华毫不妥协的悲观主义观点，即对人类个体来说，最好的境况是不曾出生，只有圣人般的自我否定（摒弃欲望）才能赋予生命价值。本书展示的叔本华，是一个具有战斗精神、气势咄咄逼人、影响力非凡的思想家。","lastChapterIdx":34,"paperBook":{"skuId":"12499882"},"chapterSize":34,"updateTime":1604246404,"onTime":1493114447,"unitPrice":0.05,"marketType":0,"isbn":"9787544732710","publisher":"译林出版社","publishTime":"2013-01-01 00:00:00","totalWords":80292,"publishPrice":25.00,"bookSize":505878,"recommended":0,"lectureRecommended":0,"follow":0,"secret":0,"offline":0,"lectureOffline":0,"finishReading":0,"isAutoPay":0,"availables":0,"paid":0,"isChapterPaid":0,"showLectureButton":1,"wxtts":1,"star":83,"ratingCount":236,"ratingDetail":{"one":3,"two":2,"three":17,"four":78,"five":132,"recent":0},"newRating":768,"newRatingCount":220,"newRatingDetail":{"good":169,"fair":49,"poor":2,"recent":0,"myRating":"","title":""},"copyrightInfo":{"id":2000000244,"name":"译林出版社","userVid":309077157},"authorSeg":[{"words":"克里斯托弗·贾纳韦","highlight":1}]}