{"bookId":"851872","title":"水浒后传","author":"陈忱","cover":"https://wfqqreader-1252317822.image.myqcloud.com/cover/872/851872/s_851872.jpg","version":1267896038,"format":"epub","type":0,"price":9.00,"originalPrice":0,"soldout":0,"bookStatus":1,"payType":4097,"finished":1,"maxFreeChapter":12,"free":0,"mcardDiscount":0,"ispub":1,"cpid":2000000366,"centPrice":900,"category":"文学榜-古典文学","hasLecture":0,"intro":"《水浒后传》成书于康熙年间，所创作的年代正值清王朝在全国的统治已基本确立之时，但各地民间反清运动仍此起彼伏。全书继承和延续了《水浒传》的主题精神，叙述了《水浒传》中幸存的李俊、阮小七、李立、燕青等三十余位梁山泊好汉及部分先烈英雄后代的坎坷命运。由于奸臣当道，迫害忠良，加上外敌入侵，抗金斗争，使得社会动荡不安，黎民百姓饱受内外压迫，民不聊生，最终让幸存的梁山好汉们再次聚义，再度造反，在登云山、饮马川等地拉起人马，对抗官府。","lastChapterIdx":43,"paperBook":{"skuId":""},"chapterSize":43,"updateTime":1615246422,"onTime":1492395823,"unitPrice":0.05,"marketType":0,"isbn":"9787508081793","publisher":"华夏出版社","publishTime":"2014-09-01 00:00:00","totalWords":256829,"publishPrice":18.00,"bookSize":1402691,"recommended":0,"lectureRecommended":0,"follow":0,"secret":0,"offline":0,"lectureOffline":0,"finishReading":0,"isAutoPay":0,"availables":0,"paid":0,"isChapterPaid":0,"showLectureButton":1,"wxtts":1,"star":79,"ratingCount":508,"ratingDetail":{"one":25,"two":18,"three":69,"four":113,"five":267,"recent":5},"newRating":653,"newRatingCount":455,"newRatingDetail":{"good":297,"fair":137,"poor":21,"recent":5,"myRating":"","title":""},"copyrightInfo":{"id":2000000366,"name":"华夏出版社","userVid":0},"authorSeg":[{"words":"陈忱","highlight":1}]}