{"bookId":"855113","title":"论美国的民主（全集）","author":"托克维尔","cover":"https://wfqqreader-1252317822.image.myqcloud.com/cover/113/855113/s_855113.jpg","version":1339409692,"format":"epub","type":0,"price":9.99,"originalPrice":0,"soldout":0,"bookStatus":1,"payType":4097,"finished":1,"maxFreeChapter":29,"free":0,"mcardDiscount":0,"ispub":1,"cpid":2000000386,"centPrice":999,"category":"政治军事榜-政治","hasLecture":0,"intro":"《论美国的民主（全集）》不只是泛泛地介绍美国的政治制度，还从社会学角度，分析美国民主的成因和发展，阐述了作者的政治哲学和政治社会学思想。涵盖面极广，相当于一部关于美国的“小百科全书”，论述内容包括美国地理环境、种族状况、移民对北美的影响、美国联邦制的优缺点以及与其他国家制度的比较等，还分析了美国人的民族性格、哲学观念、宗教思想、文学艺术，是一部不可多得的社会学著作。","lastChapterIdx":100,"paperBook":{"skuId":""},"chapterSize":100,"updateTime":1586386319,"onTime":1492756812,"unitPrice":0,"marketType":0,"isbn":"9787569909395","publisher":"北京时代华文书局","publishTime":"2016-09-01 00:00:00","totalWords":531796,"publishPrice":66.00,"bookSize":2555525,"recommended":0,"lectureRecommended":0,"follow":0,"secret":0,"offline":0,"lectureOffline":0,"finishReading":0,"isAutoPay":0,"availables":0,"paid":0,"isChapterPaid":0,"showLectureButton":1,"wxtts":1,"star":84,"ratingCount":710,"ratingDetail":{"one":19,"two":8,"three":56,"four":141,"five":463,"recent":13},"newRating":797,"newRatingCount":556,"newRatingDetail":{"good":443,"fair":97,"poor":16,"recent":10,"myRating":"","title":"值得一读"},"copyrightInfo":{"id":2000000386,"name":"时代华文书局","userVid":0},"authorSeg":[{"words":"托克维尔","highlight":1}]}