{"bookId":"907585","title":"滚雪球：巴菲特和他的财富人生（套装共2册）","author":"艾丽斯·施罗德","cover":"https://wfqqreader-1252317822.image.myqcloud.com/cover/585/907585/s_907585.jpg","version":295087007,"format":"epub","type":0,"price":58.80,"originalPrice":0,"soldout":0,"bookStatus":1,"payType":4097,"finished":1,"maxFreeChapter":18,"free":0,"mcardDiscount":0,"ispub":1,"cpid":2000000231,"centPrice":5880,"category":"传记榜-财经人物","hasLecture":1,"intro":"《滚雪球》一书为我们描述了一个和普通人一样遭遇过挫折和失败的巴菲特，如何在投资和商业中获得了巨大成功和财富。同时，《滚雪球》中对于巴菲特投资理念和商业思想的全面解读，让这位我们这个时代硕果仅存的商业领袖的精神财富，得以传承后世。","lastChapterIdx":78,"paperBook":{"skuId":""},"chapterSize":78,"updateTime":1617551855,"onTime":1568016629,"unitPrice":0.05,"marketType":0,"isbn":"","publisher":"中信出版社","publishTime":"2017-06-01 00:00:00","totalWords":727794,"publishPrice":98.00,"bookSize":3258262,"recommended":0,"lectureRecommended":0,"follow":0,"secret":0,"offline":0,"lectureOffline":0,"finishReading":0,"isAutoPay":0,"availables":0,"paid":0,"isChapterPaid":0,"showLectureButton":1,"wxtts":1,"relatedBookIds":["908151","908152","3000007076"],"star":87,"ratingCount":823,"ratingDetail":{"one":15,"two":6,"three":33,"four":111,"five":640,"recent":20},"newRating":855,"newRatingCount":716,"newRatingDetail":{"good":612,"fair":92,"poor":12,"recent":20,"myRating":"","title":"好评如潮"},"copyrightInfo":{"id":2000000231,"name":"中信出版集团","userVid":168010251},"authorSeg":[{"words":"艾丽斯·施罗德","highlight":1}]}