{"bookId":"911377","title":"心理学与微表情微反应","author":"姚尧","cover":"https://wfqqreader-1252317822.image.myqcloud.com/cover/377/911377/s_911377.jpg","version":1575928872,"format":"epub","type":0,"price":11.99,"originalPrice":0,"soldout":0,"bookStatus":1,"payType":4097,"finished":1,"maxFreeChapter":5,"free":0,"mcardDiscount":0,"ispub":1,"cpid":2000000124,"centPrice":1199,"category":"心理榜-心理学综合","hasLecture":0,"intro":"本书以心理学知识为依托，以人的微表情、微反应为对象，介绍给读者朋友一些有效促进人际交往的实用方法。","lastChapterIdx":15,"paperBook":{"skuId":""},"chapterSize":15,"updateTime":1600715042,"onTime":1508319705,"unitPrice":0.05,"marketType":0,"isbn":"9787509348567","publisher":"中国法制出版社","publishTime":"2014-01-01 00:00:00","totalWords":104899,"publishPrice":36.00,"bookSize":627766,"recommended":0,"lectureRecommended":0,"follow":0,"secret":0,"offline":0,"lectureOffline":0,"finishReading":0,"isAutoPay":0,"availables":0,"paid":0,"isChapterPaid":0,"showLectureButton":1,"wxtts":1,"star":75,"ratingCount":177,"ratingDetail":{"one":10,"two":18,"three":39,"four":24,"five":65,"recent":1},"newRating":474,"newRatingCount":152,"newRatingDetail":{"good":72,"fair":70,"poor":10,"recent":1,"myRating":"","title":""},"copyrightInfo":{"id":2000000124,"name":"中国法制出版社","userVid":0},"authorSeg":[{"words":"姚尧","highlight":1}]}