{"bookId":"912302","title":"日本新中产阶级","author":"傅高义","cover":"https://wfqqreader-1252317822.image.myqcloud.com/cover/302/912302/s_912302.jpg","version":1435939756,"format":"epub","type":0,"price":29.99,"originalPrice":0,"soldout":0,"bookStatus":1,"payType":4097,"finished":1,"maxFreeChapter":7,"free":0,"mcardDiscount":0,"ispub":1,"cpid":2000000504,"centPrice":2999,"category":"社会文化榜-社科","hasLecture":1,"intro":"哈佛大学中日研究专家傅高义在学术生涯之初被斥为“乡下人”后，意识到一个社会学家如果从未在另一种文化中生活过，何谈理解本国社会？一九五八年至一九六〇年，他来到东京市郊的M町展开田野研究，深描日本社会快速变迁之际的“新中产阶级”——工薪族和他们的家庭。二战后日本经济的迅速发展，大批职员进入大型企业与组织并得到终身职位，他们取代了老中产阶级，带动了家庭、经济与文化的变革，不仅是社会巨变中持续不辍的稳定力量，更建构了延续迄今的日本社会运作基本模式。《日本新中产阶级》是傅高义的成名之作，其主体研究耗时2年，但傅高义夫妇此后一直坚持研究对象的跟踪随访，研究成果实则跨越30年。","lastChapterIdx":25,"paperBook":{"skuId":"12182578"},"chapterSize":25,"updateTime":1615362076,"onTime":1511344933,"unitPrice":0.05,"marketType":0,"isbn":"9787532774036","publisher":"上海译文出版社","publishTime":"2017-05-01 00:00:00","totalWords":225785,"publishPrice":60.00,"bookSize":1764135,"recommended":0,"lectureRecommended":0,"follow":0,"secret":0,"offline":0,"lectureOffline":0,"finishReading":0,"isAutoPay":0,"availables":0,"paid":0,"isChapterPaid":0,"showLectureButton":1,"wxtts":1,"star":83,"ratingCount":1174,"ratingDetail":{"one":16,"two":18,"three":144,"four":417,"five":543,"recent":6},"newRating":716,"newRatingCount":1044,"newRatingDetail":{"good":748,"fair":283,"poor":13,"recent":6,"myRating":"","title":"值得一读"},"copyrightInfo":{"id":2000000504,"name":"上海译文出版社","userVid":331381138},"authorSeg":[{"words":"傅高义","highlight":1}]}