{"bookId":"913196","title":"生活是很好玩的","author":"汪曾祺","cover":"https://wfqqreader-1252317822.image.myqcloud.com/cover/196/913196/s_913196.jpg","version":499362832,"format":"epub","type":0,"price":13.99,"originalPrice":0,"soldout":0,"bookStatus":1,"payType":4097,"finished":1,"maxFreeChapter":12,"free":0,"mcardDiscount":0,"ispub":1,"cpid":2000000386,"centPrice":1399,"category":"文学榜-随笔文集","hasLecture":1,"intro":"好玩，是一种生活的体验，是一种发现和欣喜，它源于对生活无比的爱。汪曾祺说，人活着，就得有点兴致。写字、画画、做饭，明明是最普通的日常，他却深得其乐。他经历了人世的复杂，却天真得像个孩子，贪吃、贪唱、贪看、贪玩儿，对生活充满兴趣，不管在什么环境下，永远不消沉，无心机，少俗虑。鹦鹉史航说，这世间可爱的老头儿很多，但可爱成汪曾祺这样的，却不常见。凡人琐事、市井人生、花鸟虫鱼、旅行见闻，在汪曾祺的笔下散发着温暖的快乐和不凡的趣味。","lastChapterIdx":45,"paperBook":{"skuId":"12087169"},"chapterSize":45,"updateTime":1615364903,"onTime":1506250386,"unitPrice":0.05,"marketType":0,"isbn":"9787569915075","publisher":"北京时代华文书局","publishTime":"2017-06-01 00:00:00","totalWords":101257,"publishPrice":45.00,"bookSize":545494,"recommended":0,"lectureRecommended":0,"follow":0,"secret":0,"offline":0,"lectureOffline":0,"finishReading":0,"isAutoPay":0,"availables":0,"paid":0,"isChapterPaid":0,"showLectureButton":1,"wxtts":1,"star":86,"ratingCount":25166,"ratingDetail":{"one":188,"two":250,"three":1818,"four":6178,"five":13826,"recent":112},"newRating":765,"newRatingCount":21025,"newRatingDetail":{"good":16077,"fair":4794,"poor":154,"recent":104,"myRating":"","title":"值得一读"},"copyrightInfo":{"id":2000000386,"name":"时代华文书局","userVid":0},"authorSeg":[{"words":"汪曾祺","highlight":1}]}