{"bookId":"923051","title":"把碎片化时间用起来","author":"野口悠纪雄","cover":"https://wfqqreader-1252317822.image.myqcloud.com/cover/51/923051/s_923051.jpg","version":1888707267,"format":"epub","type":0,"price":16.99,"originalPrice":0,"soldout":0,"bookStatus":1,"payType":4097,"finished":1,"maxFreeChapter":13,"free":0,"mcardDiscount":0,"ispub":1,"cpid":60041,"centPrice":1699,"category":"个人成长榜-人生哲学","hasLecture":0,"intro":"野口悠纪雄在《把碎片化时间用起来》中主要讨论了节约联系和寻找文件过程中的时间管理。技术进步让我们的工作更加便捷：交通设施的发达缩短了出行时间；通信技术的进步使联系更加及时化；电脑的普及提高了个人的工作效率……可是，仅仅依靠技术进步，并不能产生富余的时间。我们要高效完成工作，更需要时间管理的新技巧。希望这本书可以教你识别“时间小偷”，帮你发现碎片时间中隐藏的超额价值，让你的每分钟都过得有意义。","lastChapterIdx":46,"paperBook":{"skuId":""},"chapterSize":46,"updateTime":1605268370,"onTime":1528442745,"unitPrice":0.05,"marketType":0,"isbn":"9787514218985","publisher":"文化发展出版社","publishTime":"2017-10-01 00:00:00","totalWords":103296,"publishPrice":39.79,"bookSize":610076,"recommended":0,"lectureRecommended":0,"follow":0,"secret":0,"offline":0,"lectureOffline":0,"finishReading":0,"isAutoPay":0,"availables":0,"paid":0,"isChapterPaid":0,"showLectureButton":1,"wxtts":1,"star":70,"ratingCount":180,"ratingDetail":{"one":26,"two":20,"three":47,"four":29,"five":57,"recent":2},"newRating":376,"newRatingCount":165,"newRatingDetail":{"good":62,"fair":78,"poor":25,"recent":2,"myRating":"","title":""},"copyrightInfo":{"id":60041,"name":"磨铁数盟","userVid":351681843},"authorSeg":[{"words":"野口悠纪雄","highlight":1}]}