{"bookId":"923973","title":"胡适谈读书与做人","author":"胡适","cover":"https://wfqqreader-1252317822.image.myqcloud.com/cover/973/923973/s_923973.jpg","version":76602073,"format":"epub","type":0,"price":11.99,"originalPrice":0,"soldout":0,"bookStatus":1,"payType":4097,"finished":1,"maxFreeChapter":8,"free":0,"mcardDiscount":0,"ispub":1,"cpid":2000000113,"centPrice":1199,"category":"文学榜-随笔文集","hasLecture":0,"intro":"《胡适谈读书与做人》精选著名学者胡适论读书与论人生的24篇文章。选录文章时，秉着循序渐进、兼收并蓄的原则，内容读起来一脉相承，蕴藏万千。“谈读书”从读书的原因讲起，再论读书的方法、习惯、乐趣，并夹以文学评论、文学创新倡议；“谈做人”先总论人生，进而谈论容忍与自由，修养与哲学，指导人们更好地理解人生。","lastChapterIdx":27,"paperBook":{"skuId":""},"chapterSize":27,"updateTime":1600717702,"onTime":1517823121,"unitPrice":0.05,"marketType":0,"isbn":"9787513910989","publisher":"民主与建设出版社","publishTime":"2017-06-01 00:00:00","totalWords":81054,"publishPrice":39.80,"bookSize":349112,"recommended":0,"lectureRecommended":0,"follow":0,"secret":0,"offline":0,"lectureOffline":0,"finishReading":0,"isAutoPay":0,"availables":0,"paid":0,"isChapterPaid":0,"showLectureButton":1,"wxtts":1,"star":84,"ratingCount":477,"ratingDetail":{"one":3,"two":4,"three":25,"four":104,"five":301,"recent":3},"newRating":799,"newRatingCount":407,"newRatingDetail":{"good":325,"fair":79,"poor":3,"recent":3,"myRating":"","title":""},"copyrightInfo":{"id":2000000113,"name":"紫云文心","userVid":0},"authorSeg":[{"words":"胡适","highlight":1}]}